tiktalik/__init__.py
tiktalik/apiobject.py
tiktalik/connection.py
tiktalik/error.py
tiktalik/objects.py
tiktalik-2.0.0.dist-info/WHEEL
tiktalik-2.0.0.dist-info/METADATA
tiktalik-2.0.0.dist-info/RECORD
