Metadata-Version: 2.4
Name: tiktalik
Version: 2.0.0
Summary: Python SDK for the Tiktalik Computing service
Keywords: SDK,Tiktalik,VPS
Author: Techstorage sp. z o.o
Author-email: Techstorage sp. z o.o <kontakt@tiktalik.com>
License-Expression: MIT
Classifier: Programming Language :: Python :: 3
Classifier: Programming Language :: Python :: 3.10
Classifier: Programming Language :: Python :: 3.11
Classifier: Programming Language :: Python :: 3.12
Classifier: Programming Language :: Python :: 3.13
Classifier: Programming Language :: Python :: 3.14
Classifier: Topic :: Internet
Classifier: Topic :: Software Development :: Libraries
Classifier: License :: OSI Approved :: MIT License
Classifier: Development Status :: 5 - Production/Stable
Classifier: Intended Audience :: Developers
Requires-Dist: httpx[brotli,http2,zstd]>=0.28.1
Requires-Python: >=3.10
Project-URL: Homepage, https://www.tiktalik.com
Project-URL: Repository, https://github.com/tiktalik-cloud/tiktalik-python.git
